LICENSE
MANIFEST.in
README.md
setup.py
mycroft_porcupine_plugin/__init__.py
mycroft_porcupine_plugin.egg-info/PKG-INFO
mycroft_porcupine_plugin.egg-info/SOURCES.txt
mycroft_porcupine_plugin.egg-info/dependency_links.txt
mycroft_porcupine_plugin.egg-info/entry_points.txt
mycroft_porcupine_plugin.egg-info/requires.txt
mycroft_porcupine_plugin.egg-info/top_level.txt