Metadata-Version: 2.1
Name: mycroft-porcupine-plugin
Version: 0.1.1
Summary: A Porcupine wakeword plugin for mycroft
Home-page: UNKNOWN
Author: Åke Forslund
Author-email: ake.forslund@gmail.com
License: UNKNOWN
Keywords: mycroft plugin tts
Platform: UNKNOWN
